__init__.py
ustr.py
ustr-0.0.2.dist-info/LICENSE
ustr-0.0.2.dist-info/METADATA
ustr-0.0.2.dist-info/WHEEL
ustr-0.0.2.dist-info/top_level.txt
ustr-0.0.2.dist-info/RECORD
